MicroHMM/__init__.py
MicroHMM/forward.py
MicroHMM/hmm.py
MicroHMM/viterbi.py
MicroHMM-0.4.3.dist-info/METADATA
MicroHMM-0.4.3.dist-info/RECORD
MicroHMM-0.4.3.dist-info/WHEEL
MicroHMM-0.4.3.dist-info/top_level.txt
