Metadata-Version: 2.1
Name: MicroHMM
Version: 0.4.3
Summary: A micro python package for HMM model
Home-page: https://github.com/howl-anderson/MicroHMM
Author: Xiaoquan Kong
Author-email: u1mail2me@gmail.com
License: MIT
Platform: UNKNOWN
Requires-Dist: networkx
Requires-Dist: pathlib; python_version < "3.4"
Requires-Dist: typing; python_version < "3.5"
